src/__init__.py
src/__main__.py
src/douban.py
src/view.py
douban_movie-0.0.4.dist-info/METADATA
douban_movie-0.0.4.dist-info/WHEEL
douban_movie-0.0.4.dist-info/entry_points.txt
douban_movie-0.0.4.dist-info/top_level.txt
douban_movie-0.0.4.dist-info/RECORD
