Metadata-Version: 2.1
Name: douban-movie
Version: 0.0.4
Summary: Get movie info from Douban (豆瓣) and display in your terminal
Home-page: https://github.com/chishui/douban-movie
Author: Liyun Xiu
Author-email: chishui2@gmail.com
License: MIT
Keywords: douban terminal movie
Platform: UNKNOWN
Requires-Dist: requests
Requires-Dist: bs4
Requires-Dist: lxml
Requires-Dist: urwid
